odoo/addons/stock_picking_report_delivery_cost/README.rst
odoo/addons/stock_picking_report_delivery_cost/__init__.py
odoo/addons/stock_picking_report_delivery_cost/__manifest__.py
odoo/addons/stock_picking_report_delivery_cost/i18n/es.po
odoo/addons/stock_picking_report_delivery_cost/i18n/stock_picking_report_delivery_cost.pot
odoo/addons/stock_picking_report_delivery_cost/models/__init__.py
odoo/addons/stock_picking_report_delivery_cost/models/stock_picking.py
odoo/addons/stock_picking_report_delivery_cost/readme/CONTRIBUTORS.rst
odoo/addons/stock_picking_report_delivery_cost/readme/DESCRIPTION.rst
odoo/addons/stock_picking_report_delivery_cost/readme/USAGE.rst
odoo/addons/stock_picking_report_delivery_cost/report/report_deliveryslip.xml
odoo/addons/stock_picking_report_delivery_cost/report/report_shipping.xml
odoo/addons/stock_picking_report_delivery_cost/static/description/icon.png
odoo/addons/stock_picking_report_delivery_cost/static/description/index.html
odoo/addons/stock_picking_report_delivery_cost/tests/__init__.py
odoo/addons/stock_picking_report_delivery_cost/tests/test_stock_picking_report_delivery_cost.py
odoo11_addon_stock_picking_report_delivery_cost-11.0.1.0.0.99.dev3.dist-info/METADATA
odoo11_addon_stock_picking_report_delivery_cost-11.0.1.0.0.99.dev3.dist-info/WHEEL
odoo11_addon_stock_picking_report_delivery_cost-11.0.1.0.0.99.dev3.dist-info/top_level.txt
odoo11_addon_stock_picking_report_delivery_cost-11.0.1.0.0.99.dev3.dist-info/RECORD
